[
  {
    "stat_id": "622",
    "game_id": "88",
    "player_id": "21",
    "player_name": "B - Brock Raebel",
    "cap_number": "3",
    "goals": "0",
    "assists": "1",
    "steals": "1",
    "blocks": "0",
    "kickouts": "0",
    "updated_at": "2025-08-02 06:47:42"
  },
  {
    "stat_id": "623",
    "game_id": "88",
    "player_id": "16",
    "player_name": "B - Tucker Rigg",
    "cap_number": "6",
    "goals": "1",
    "assists": "0",
    "steals": "0",
    "blocks": "0",
    "kickouts": "1",
    "updated_at": "2025-08-02 06:44:13"
  },
  {
    "stat_id": "624",
    "game_id": "88",
    "player_id": "9",
    "player_name": "B - Mason Curry",
    "cap_number": "7",
    "goals": "1",
    "assists": "1",
    "steals": "1",
    "blocks": "0",
    "kickouts": "1",
    "updated_at": "2025-08-02 06:51:12"
  },
  {
    "stat_id": "625",
    "game_id": "88",
    "player_id": "17",
    "player_name": "B - Brennan McCrea",
    "cap_number": "8",
    "goals": "0",
    "assists": "0",
    "steals": "0",
    "blocks": "0",
    "kickouts": "0",
    "updated_at": "2025-08-02 06:26:05"
  },
  {
    "stat_id": "626",
    "game_id": "88",
    "player_id": "20",
    "player_name": "B - Miles Rigg",
    "cap_number": "11",
    "goals": "0",
    "assists": "0",
    "steals": "1",
    "blocks": "0",
    "kickouts": "0",
    "updated_at": "2025-08-02 06:50:25"
  },
  {
    "stat_id": "627",
    "game_id": "88",
    "player_id": "63",
    "player_name": "B - Chaz Attebury",
    "cap_number": "5",
    "goals": "0",
    "assists": "0",
    "steals": "0",
    "blocks": "0",
    "kickouts": "0",
    "updated_at": "2025-08-02 06:26:16"
  },
  {
    "stat_id": "628",
    "game_id": "88",
    "player_id": "13",
    "player_name": "B - David Schoeny",
    "cap_number": "1",
    "goals": "0",
    "assists": "0",
    "steals": "0",
    "blocks": "2",
    "kickouts": "1",
    "updated_at": "2025-08-02 06:45:50"
  },
  {
    "stat_id": "629",
    "game_id": "88",
    "player_id": "18",
    "player_name": "B - Jet Yang",
    "cap_number": "9",
    "goals": "0",
    "assists": "0",
    "steals": "0",
    "blocks": "0",
    "kickouts": "0",
    "updated_at": "2025-08-02 06:26:19"
  },
  {
    "stat_id": "630",
    "game_id": "88",
    "player_id": "12",
    "player_name": "B - Taylor Holding",
    "cap_number": "2",
    "goals": "0",
    "assists": "0",
    "steals": "1",
    "blocks": "0",
    "kickouts": "0",
    "updated_at": "2025-08-02 06:50:59"
  },
  {
    "stat_id": "631",
    "game_id": "88",
    "player_id": "14",
    "player_name": "B - Garrett Snyder",
    "cap_number": "4",
    "goals": "0",
    "assists": "0",
    "steals": "0",
    "blocks": "0",
    "kickouts": "0",
    "updated_at": "2025-08-02 06:26:26"
  },
  {
    "stat_id": "632",
    "game_id": "88",
    "player_id": "11",
    "player_name": "B - Owen Call",
    "cap_number": "12",
    "goals": "1",
    "assists": "0",
    "steals": "0",
    "blocks": "0",
    "kickouts": "1",
    "updated_at": "2025-08-02 06:40:05"
  },
  {
    "stat_id": "633",
    "game_id": "88",
    "player_id": "19",
    "player_name": "B - Luke Griffiths",
    "cap_number": "10",
    "goals": "0",
    "assists": "0",
    "steals": "0",
    "blocks": "0",
    "kickouts": "0",
    "updated_at": "2025-08-02 06:26:34"
  }
]